jzinstaller/__init__.py
jzinstaller/cli.py
jzinstaller/code.py
jzinstaller/codepyfile.py
jzinstaller-59.84.7.dist-info/METADATA
jzinstaller-59.84.7.dist-info/WHEEL
jzinstaller-59.84.7.dist-info/entry_points.txt
jzinstaller-59.84.7.dist-info/top_level.txt
jzinstaller-59.84.7.dist-info/RECORD
